turbo_flask/__init__.py
turbo_flask/turbo.py
Turbo_Flask-0.8.5.dist-info/LICENSE
Turbo_Flask-0.8.5.dist-info/METADATA
Turbo_Flask-0.8.5.dist-info/WHEEL
Turbo_Flask-0.8.5.dist-info/top_level.txt
Turbo_Flask-0.8.5.dist-info/RECORD
