Metadata-Version: 2.1
Name: Turbo-Flask
Version: 0.8.5
Summary: Use Hotwire Turbo in your Flask application.
Author-email: Miguel Grinberg <miguel.grinberg@gmail.com>
Project-URL: Homepage, https://github.com/miguelgrinberg/turbo-flask
Project-URL: Bug Tracker, https://github.com/miguelgrinberg/turbo-flask/issues
Classifier: Environment :: Web Environment
Classifier: Intended Audience :: Developers
Classifier: Programming Language :: Python :: 3
Classifier: License :: OSI Approved :: MIT License
Classifier: Operating System :: OS Independent
Requires-Python: >=3.6
License-File: LICENSE
Requires-Dist: flask>=2
Requires-Dist: flask-sock>=0.4
Provides-Extra: docs
Requires-Dist: sphinx; extra == "docs"
